wnet-0.9.4.dist-info/RECORD
wnet-0.9.4.dist-info/WHEEL
wnet-0.9.4.dist-info/METADATA
wnet-0.9.4.dist-info/licenses/LICENCE
wnet/wasserstein_network.py
wnet/distances.py
wnet/__init__.py
wnet/distribution.py
wnet/wnet_cpp.cpython-314t-darwin.so
wnet/wasserstein.py
wnet/__main__.py
wnet/cpp/wnet/example.cpp
wnet/cpp/wnet/wnet.cpp
wnet/cpp/wnet/decompositable_graph.hpp
wnet/cpp/wnet/graph_elements.hpp
wnet/cpp/wnet/distribution.hpp
wnet/cpp/wnet/misc.hpp
