Metadata-Version: 2.4
Name: wnet
Version: 0.9.4
Summary: Tools for calculation of Wasserstein metric between distributions based on Network Flow algorithm
Keywords: Wasserstein,Optimal Transport,Network Flow,Earth Mover's Distance
Author-Email: =?utf-8?q?Micha=C5=82_Startek?= <michal.startek@mimuw.edu.pl>
Maintainer-Email: =?utf-8?q?Micha=C5=82_Startek?= <michal.startek@mimuw.edu.pl>
License-Expression: MIT
License-File: LICENCE
Classifier: Programming Language :: Python :: 3
Classifier: Topic :: Scientific/Engineering :: Mathematics
Classifier: Topic :: Software Development :: Libraries :: Python Modules
Classifier: Development Status :: 4 - Beta
Project-URL: Homepage, https://github.com/michalsta/wnet
Project-URL: Repository, https://github.com/michalsta/wnet.git
Requires-Python: >=3.9
Requires-Dist: pylmcf
Requires-Dist: numpy
Provides-Extra: extras
Requires-Dist: networkx; extra == "extras"
Requires-Dist: matplotlib; extra == "extras"
Provides-Extra: pytest
Requires-Dist: pytest; extra == "pytest"
